{
  "appearance": [
    "scar across the cheek",
    "piercing gray eyes",
    "oil-stained hands",
    "immaculate uniform",
    "mud-caked boots",
    "gold tooth",
    "tattoos of old battles",
    "smells faintly of incense",
    "sun-bleached hair",
    "nervous fidget",
    "weathered skin",
    "calloused knuckles",
    "missing finger",
    "shaved head",
    "braided beard",
    "cracked lips",
    "dusty cloak",
    "patched coat",
    "embroidered sash",
    "rust-stained armor",
    "polished boots",
    "ink-stained fingertips",
    "smoke-scarred hair",
    "fresh bruises",
    "limp from old wound",
    "twitchy eye",
    "bright scarf",
    "scarred knuckles",
    "sunken cheeks",
    "sunburned nose",
    "missing tooth",
    "stained apron",
    "sleeves rolled up",
    "bandaged forearm",
    "ringed fingers",
    "tattooed forearms",
    "chipped nail polish",
    "hood pulled low",
    "cloak of many patches",
    "mud on hem",
    "smells of pine",
    "smells of ink",
    "smells of ale",
    "perfumed hair",
    "mud-splattered calves",
    "heavy eyeliner",
    "bright blue eyes",
    "jagged ear",
    "nose ring",
    "silver spectacles",
    "scar over eyebrow",
    "burn mark on neck",
    "tattoo behind ear",
    "gloves with cut fingers",
    "worn holy symbol",
    "ribbon tied to wrist",
    "stiff posture",
    "slouched shoulders",
    "fast restless hands",
    "smudged face paint",
    "old military badge",
    "fresh haircut",
    "unkempt hair",
    "braided hair",
    "shaved temples",
    "dusty boots",
    "polished dagger",
    "weapon always visible"
  ],
  "speech": [
    "slow and deliberate",
    "fast and clipped",
    "soft-spoken",
    "booming voice",
    "dry humor",
    "formal and polite",
    "street slang",
    "whispers when nervous",
    "measured and calm",
    "rapid and nervous",
    "cheerful and loud",
    "mumbles under breath",
    "overly precise",
    "singsong tone",
    "thick accent",
    "rolling r's",
    "short sentences",
    "rambling stories",
    "sharp sarcasm",
    "warm and friendly",
    "cold and clipped",
    "gravelly voice",
    "high-pitched",
    "voice cracks",
    "stutters when stressed",
    "overconfident",
    "avoids eye contact",
    "uses many titles",
    "asks constant questions",
    "never uses contractions",
    "laughs at own jokes",
    "counts while speaking",
    "slow drawl",
    "precise enunciation",
    "poetic phrasing",
    "speaks in proverbs",
    "rapid fire questions"
  ],
  "motivations": [
    "protect a loved one",
    "clear a family debt",
    "prove their worth",
    "seek forbidden knowledge",
    "hide a past crime",
    "gain political favor",
    "avenge a friend",
    "keep a secret safe",
    "escape a curse",
    "find a lost sibling",
    "earn a noble title",
    "break a rival guild",
    "protect their reputation",
    "secure a safe retirement",
    "win a tournament",
    "find a cure",
    "pay back a mentor",
    "complete a prophecy",
    "restore a relic",
    "free a captive",
    "map a dangerous region",
    "settle a blood feud",
    "build a new business",
    "fund a rebellion",
    "win a bet",
    "protect a village",
    "collect rare artifacts",
    "expose a conspiracy",
    "get rich quick",
    "keep their job",
    "save face",
    "impress a lover",
    "secure a trade route",
    "earn redemption",
    "destroy a cult",
    "become famous",
    "find true identity",
    "repay a favor",
    "avoid a debt collector",
    "prove a theory"
  ],
  "secrets": [
    "working for a rival faction",
    "addicted to rare elixirs",
    "has a hidden heirloom",
    "covers for a missing mentor",
    "blackmailed by a noble",
    "knows the villain's weakness",
    "secretly ill",
    "has a second family",
    "stole a sacred relic",
    "owes a demon",
    "is an undercover agent",
    "framed for a crime",
    "wanted in another city",
    "sold out a friend",
    "secretly a noble",
    "hiding magical talent",
    "smuggling contraband",
    "forged their papers",
    "is a deserter",
    "poisoned their rival",
    "has a cursed item",
    "keeps a forbidden diary",
    "betrayed their guild",
    "owes a blood debt",
    "paid by a cult",
    "is hiding a bounty",
    "stashed a fortune",
    "is not who they claim",
    "secretly illiterate",
    "took a fall for someone",
    "lost a sacred oath",
    "is being watched",
    "secretly a spy",
    "faked their death",
    "hiding from family",
    "lied about their past",
    "has a fake identity",
    "harbors a fugitive",
    "made a dark pact",
    "stole a map"
  ],
  "hooks": [
    "offers a job that pays in favors",
    "asks for discreet protection",
    "needs help smuggling a package",
    "wants an escort through dangerous roads",
    "seeks a lost map fragment",
    "witnessed something they should not have",
    "needs a bodyguard for a meeting",
    "offers access to a hidden library",
    "needs help covering a crime",
    "asks to deliver a sealed letter",
    "has a lead on a missing person",
    "needs a guide through ruins",
    "offers a reward for a stolen item",
    "asks to sabotage a rival",
    "needs help breaking a curse",
    "seeks witnesses for a trial",
    "asks to retrieve a ledger",
    "needs a distraction",
    "offers a secret tunnel",
    "asks for help with a heist",
    "needs help mapping a cave",
    "offers a trade contact",
    "asks to test an invention",
    "needs help escaping guards",
    "offers a rare potion",
    "asks to find a hidden shrine",
    "needs escort for a caravan",
    "offers a bounty lead",
    "asks for a duel",
    "needs help recovering cargo",
    "asks to find a lost pet",
    "offers a safehouse",
    "needs help forging papers",
    "asks to deliver a message",
    "needs help catching a thief",
    "offers a blackmail dossier",
    "asks to protect a witness",
    "needs help at a ritual",
    "asks to scout a camp",
    "needs help securing a relic"
  ],
  "quirks": [
    "counts coins twice",
    "avoids eye contact",
    "always sharpening a blade",
    "collects odd trinkets",
    "hums old marching songs",
    "keeps a tiny journal",
    "snaps fingers when thinking",
    "taps foot constantly",
    "repeats your last word",
    "never sits with back exposed",
    "chews on a toothpick",
    "always late",
    "always early",
    "refuses to shake hands",
    "sips from a flask",
    "talks to their pet",
    "flips a coin",
    "polishes glasses",
    "stares into distance",
    "collects feathers",
    "names every weapon",
    "writes everything down",
    "laughs at bad news",
    "jingles keys",
    "wears mismatched socks",
    "twirls a ring",
    "never uses doors",
    "counts steps",
    "fixes hair constantly",
    "shuffles cards",
    "keeps smelling salts",
    "touches lucky charm",
    "won't sit still",
    "draws symbols on tables",
    "avoids mirrors",
    "keeps a pocket mirror",
    "speaks in rhymes",
    "whistles softly",
    "collects buttons",
    "keeps a spare pen"
  ]
}
